azure/mgmt/connectedcache/__init__.py
azure/mgmt/connectedcache/_client.py
azure/mgmt/connectedcache/_configuration.py
azure/mgmt/connectedcache/_model_base.py
azure/mgmt/connectedcache/_patch.py
azure/mgmt/connectedcache/_serialization.py
azure/mgmt/connectedcache/_version.py
azure/mgmt/connectedcache/py.typed
azure/mgmt/connectedcache/aio/__init__.py
azure/mgmt/connectedcache/aio/_client.py
azure/mgmt/connectedcache/aio/_configuration.py
azure/mgmt/connectedcache/aio/_patch.py
azure/mgmt/connectedcache/aio/operations/__init__.py
azure/mgmt/connectedcache/aio/operations/_operations.py
azure/mgmt/connectedcache/aio/operations/_patch.py
azure/mgmt/connectedcache/models/__init__.py
azure/mgmt/connectedcache/models/_enums.py
azure/mgmt/connectedcache/models/_models.py
azure/mgmt/connectedcache/models/_patch.py
azure/mgmt/connectedcache/operations/__init__.py
azure/mgmt/connectedcache/operations/_operations.py
azure/mgmt/connectedcache/operations/_patch.py
azure_mgmt_connectedcache-1.0.0b1.dist-info/LICENSE
azure_mgmt_connectedcache-1.0.0b1.dist-info/METADATA
azure_mgmt_connectedcache-1.0.0b1.dist-info/WHEEL
azure_mgmt_connectedcache-1.0.0b1.dist-info/top_level.txt
azure_mgmt_connectedcache-1.0.0b1.dist-info/RECORD
